LICENSE
README.md
pyproject.toml
chemprice/__init__.py
chemprice/chemprice.py
chemprice/utils.py
chemprice/tests/Utils.py
chemprice/tests/__init__.py
chemprice.egg-info/PKG-INFO
chemprice.egg-info/SOURCES.txt
chemprice.egg-info/dependency_links.txt
chemprice.egg-info/requires.txt
chemprice.egg-info/top_level.txt
logo/logo_chemprice_blue.png
logo/logo_chemprice_transparant.png
logo/logo_chemprice_white.png
chemprice-1.1.0.dist-info/LICENSE
chemprice-1.1.0.dist-info/METADATA
chemprice-1.1.0.dist-info/WHEEL
chemprice-1.1.0.dist-info/top_level.txt
chemprice-1.1.0.dist-info/RECORD
