Metadata-Version: 2.1
Name: chemprice
Version: 1.1.0
Summary: A python library for chemical price Search.
Home-page: https://github.com/bsaliou/ChemPrice
Author: Baptiste SALIOU
Author-email: baptiste1saliou@gmail.com
License: BSD
Project-URL: Interface, https://chemprice.streamlit.app/
Project-URL: Documentation, https://chemprice.readthedocs.io/en/latest/
Keywords: chemoinformatics
Classifier: Intended Audience :: Science/Research
Classifier: Intended Audience :: Developers
Classifier: Programming Language :: Python
Classifier: Programming Language :: Python :: 3.8
Classifier: License :: OSI Approved :: BSD License
Classifier: Operating System :: OS Independent
Classifier: Natural Language :: English
Classifier: Topic :: Scientific/Engineering
Requires-Python: >=3.6
License-File: LICENSE
Requires-Dist: requests (==2.28.1)
Requires-Dist: pandas (==1.3.5)
Requires-Dist: tqdm (==4.65.0)
